AUTHORS.txt
INSTALL.txt
LICENSE.GPL
LICENSE.txt
MANIFEST.in
README.rst
buildout.cfg
setup.cfg
setup.py
hmc/__init__.py
hmc.theme.egg-info/PKG-INFO
hmc.theme.egg-info/SOURCES.txt
hmc.theme.egg-info/dependency_links.txt
hmc.theme.egg-info/entry_points.txt
hmc.theme.egg-info/namespace_packages.txt
hmc.theme.egg-info/not-zip-safe
hmc.theme.egg-info/requires.txt
hmc.theme.egg-info/top_level.txt
hmc/theme/__init__.py
hmc/theme/configure.zcml
hmc/theme/tests.py
hmc/theme/profiles/default/metadata.xml
hmc/theme/resources/LICENSE.md
hmc/theme/resources/index.html
hmc/theme/resources/rules.xml
hmc/theme/resources/css/LICENSE
hmc/theme/resources/css/bootstrap-glyphicons.css
hmc/theme/resources/css/bootstrap.css
hmc/theme/resources/css/bootstrap.min.css
hmc/theme/resources/css/custom.css
hmc/theme/resources/css/main.css
hmc/theme/resources/css/normalize.css
hmc/theme/resources/fonts/LICENSE
hmc/theme/resources/fonts/glyphiconshalflings-regular.eot
hmc/theme/resources/fonts/glyphiconshalflings-regular.otf
hmc/theme/resources/fonts/glyphiconshalflings-regular.svg
hmc/theme/resources/fonts/glyphiconshalflings-regular.ttf
hmc/theme/resources/fonts/glyphiconshalflings-regular.woff
hmc/theme/resources/img/csu-seal.svg
hmc/theme/resources/img/favicon.ico
hmc/theme/resources/img/lab.jpg
hmc/theme/resources/img/seal.png
hmc/theme/resources/js/bootstrap.js
hmc/theme/resources/js/bootstrap.min.js
hmc/theme/resources/js/main.js
hmc/theme/resources/js/plugins.js
hmc/theme/resources/js/vendor/jquery-1.9.1.min.js
hmc/theme/resources/js/vendor/modernizr-2.6.2.min.js
hmc/theme/resources/js/vendor/respond.min.js
img/activate-theme.png
img/add-ons.png
img/front-page.png
img/theme-base.png