Metadata-Version: 1.1
Name: hmc.theme
Version: 0.1.1
Summary: The Diazo based theme for hmc.csuohio.edu.
Home-page: http://github.com/csu-hmc/hmc.theme
Author: Jason K. Moore
Author-email: j.k.moore19@csuohio.edu
License: GPL
Keywords: theme plone
Platform: UNKNOWN
Classifier: Framework :: Plone
Classifier: Programming Language :: Python
